pytest_kivy/__init__.py
pytest_kivy/_version.py
pytest_kivy/app.py
pytest_kivy/input.py
pytest_kivy/plugin.py
pytest_kivy/resolver.py
pytest_kivy/tools.py
pytest_kivy/tests/__init__.py
pytest_kivy/tests/test_app.py
pytest_kivy/tests/test_async_backend.py
pytest_kivy/tests/test_params.py
pytest_kivy/tests/test_resolver.py
pytest_kivy-0.1.0.dev2.dist-info/LICENSE
pytest_kivy-0.1.0.dev2.dist-info/METADATA
pytest_kivy-0.1.0.dev2.dist-info/WHEEL
pytest_kivy-0.1.0.dev2.dist-info/entry_points.txt
pytest_kivy-0.1.0.dev2.dist-info/top_level.txt
pytest_kivy-0.1.0.dev2.dist-info/RECORD
